mdmls/__init__.py
mdmls/main.py
mdmls/use/__init__.py
mdmls/use/cli.py
mdmls/use/summarizer.py
mdmls-0.1.3.dist-info/METADATA
mdmls-0.1.3.dist-info/WHEEL
mdmls-0.1.3.dist-info/entry_points.txt
mdmls-0.1.3.dist-info/top_level.txt
mdmls-0.1.3.dist-info/RECORD
